not1mm/__init__.py
not1mm/__main__.py
not1mm/bandmap.py
not1mm/chat.py
not1mm/checkwindow.py
not1mm/dxcc_tracker.py
not1mm/fsutils.py
not1mm/logwindow.py
not1mm/lookupservice.py
not1mm/radio.py
not1mm/ratewindow.py
not1mm/rotator.py
not1mm/rtc_service.py
not1mm/statistics.py
not1mm/test.py
not1mm/vfo.py
not1mm/voice_keying.py
not1mm/zone_tracker.py
not1mm/data/JetBrainsMono-Thin.ttf
not1mm/data/MASTER.SCP
not1mm/data/about.ui
not1mm/data/alpha bravo charlie delta.txt
not1mm/data/bandmap.ui
not1mm/data/chat.ui
not1mm/data/check.png
not1mm/data/checkwindow.ui
not1mm/data/cloud_green.png
not1mm/data/cloud_red.png
not1mm/data/configuration.ui
not1mm/data/contests.sql
not1mm/data/cty.json
not1mm/data/cwmacros.txt
not1mm/data/donors.html
not1mm/data/dxcc_tracker.ui
not1mm/data/editcontact.ui
not1mm/data/editmacro.ui
not1mm/data/greendot.png
not1mm/data/k6gte-not1mm.desktop
not1mm/data/k6gte.not1mm-128.png
not1mm/data/k6gte.not1mm-32.png
not1mm/data/k6gte.not1mm-64.png
not1mm/data/logwindow.ui
not1mm/data/logwindowx.ui
not1mm/data/main.ui
not1mm/data/map3.png
not1mm/data/new_contest.ui
not1mm/data/not1mm.html
not1mm/data/opon.ui
not1mm/data/pickcontest.ui
not1mm/data/radio_green.png
not1mm/data/radio_grey.png
not1mm/data/radio_red.png
not1mm/data/ratewindow.ui
not1mm/data/reddot.png
not1mm/data/rotator.ui
not1mm/data/rttymacros.txt
not1mm/data/settings.ui
not1mm/data/splash.png
not1mm/data/ssbmacros.txt
not1mm/data/statistics.ui
not1mm/data/vfo.ui
not1mm/data/zone_tracker.ui
not1mm/data/phonetics/0.wav
not1mm/data/phonetics/1.wav
not1mm/data/phonetics/2.wav
not1mm/data/phonetics/3.wav
not1mm/data/phonetics/4.wav
not1mm/data/phonetics/5.wav
not1mm/data/phonetics/6.wav
not1mm/data/phonetics/7.wav
not1mm/data/phonetics/73.wav
not1mm/data/phonetics/8.wav
not1mm/data/phonetics/9.wav
not1mm/data/phonetics/a.wav
not1mm/data/phonetics/again.wav
not1mm/data/phonetics/b.wav
not1mm/data/phonetics/c.wav
not1mm/data/phonetics/contest.wav
not1mm/data/phonetics/cq.wav
not1mm-26.1.31.dist-info/licenses/LICENSE
not1mm-26.1.31.dist-info/METADATA
not1mm-26.1.31.dist-info/WHEEL
not1mm-26.1.31.dist-info/entry_points.txt
not1mm-26.1.31.dist-info/top_level.txt
not1mm-26.1.31.dist-info/RECORD
