Metadata-Version: 2.4
Name: not1mm
Version: 26.1.31
Summary: NOT1MM Logger
Author-email: Michael Bridak <michael.bridak@gmail.com>
License-Expression: GPL-3.0-or-later
Project-URL: Homepage, https://github.com/mbridak/not1mm
Project-URL: Bug Tracker, https://github.com/mbridak/not1mm/issues
Classifier: Programming Language :: Python :: 3
Classifier: Development Status :: 5 - Production/Stable
Classifier: Environment :: X11 Applications :: Qt
Classifier: Operating System :: POSIX :: Linux
Classifier: Intended Audience :: End Users/Desktop
Classifier: Natural Language :: English
Classifier: Topic :: Communications :: Ham Radio
Requires-Python: >=3.10
License-File: LICENSE
Requires-Dist: PyQt6
Requires-Dist: requests
Requires-Dist: dicttoxml
Requires-Dist: xmltodict
Requires-Dist: pyserial
Requires-Dist: sounddevice
Requires-Dist: soundfile
Requires-Dist: numpy
Requires-Dist: notctyparser>=23.6.21
Requires-Dist: rapidfuzz
Requires-Dist: appdata
Requires-Dist: adif_io
Requires-Dist: sh>=2.2.2
Dynamic: license-file
